{
    "alternatives": [
        "A1",
        "A2",
        "A3"
    ],
    "gole": {
        "preferences": [],
        "children": [
            {
                "preferences": [],
                "children": [],
                "name": "F1"
            },
            {
                "preferences": [],
                "children": [
                    {
                        "preferences": [],
                        "children": [],
                        "name": "F21"
                    }
                ],
                "name": "F2"
            },
            {
                "preferences": [],
                "children": [],
                "name": "F3"
            }
        ],
        "name": "R"
    }
}